{"commit":"623a23f2c4848acdbb1a38c2689e571eb73eb823","pagesAndArtboards":{"E4DA70F4-CA97-4370-819D-46AFE2654A80":{"name":"组件库","artboards":{}},"960AE1AD-4B9F-423D-A38A-7EB7833F4274":{"name":"主页","artboards":{"886DEA86-C72A-46FF-A0F4-14ACE2456136":{"name":"EUIKit"}}}},"version":112,"fonts":["PingFangSC-Regular"],"compatibilityVersion":99,"app":"com.bohemiancoding.sketch3","autosaved":0,"variant":"NONAPPSTORE","created":{"commit":"623a23f2c4848acdbb1a38c2689e571eb73eb823","appVersion":"52.2","build":67145,"app":"com.bohemiancoding.sketch3","compatibilityVersion":99,"version":112,"variant":"NONAPPSTORE"},"saveHistory":["NONAPPSTORE.67145"],"appVersion":"52.2","build":67145}